simba/.cursorrules
simba/.gitignore
simba/README.md
simba/__init__.py
simba/__main__.py
simba/api/chat_routes.py
simba/api/database_routes.py
simba/api/dto/retriever_dto.py
simba/api/embedding_routes.py
simba/api/ingestion_routes.py
simba/api/parsing_routes.py
simba/api/retriever_routes.py
simba/chatbot/demo/__init__.py
simba/chatbot/demo/chains/__init__.py
simba/chatbot/demo/chains/answer_chain.py
simba/chatbot/demo/chains/generate_chain.py
simba/chatbot/demo/chains/grade_chain.py
simba/chatbot/demo/chains/hallucination_chain.py
simba/chatbot/demo/chains/question_rewrite_chain.py
simba/chatbot/demo/graph.py
simba/chatbot/demo/nodes/README.md
simba/chatbot/demo/nodes/__init__.py
simba/chatbot/demo/nodes/generate_node.py
simba/chatbot/demo/nodes/grade_node.py
simba/chatbot/demo/nodes/retrieve_node.py
simba/chatbot/demo/self-reflective-rag.png
simba/chatbot/demo/state.py
simba/cli.py
simba/core/.README.md
simba/core/celery_config.py
simba/core/config.py
simba/core/factories/database_factory.py
simba/core/factories/embeddings_factory.py
simba/core/factories/llm_factory.py
simba/core/factories/vector_store_factory.py
simba/core/utils/logger.py
simba/database/litedb_service.py
simba/database/sqlite_service.py
simba/database/tinydb_service.py
simba/ingestion/__init__.py
simba/ingestion/document_ingestion.py
simba/ingestion/file_handling.py
simba/ingestion/loader.py
simba/ingestion/utils.py
simba/models/simbadoc.py
simba/parsing/__init__.py
simba/parsing/base.py
simba/parsing/docling_parser.py
simba/parsing/markitdown_parser.py
simba/retrieval/__init__.py
simba/retrieval/retriever.py
simba/splitting/__init__.py
simba/splitting/splitter.py
simba/tasks/__init__.py
simba/tasks/parsing_tasks.py
simba/tests/test_config.py
simba/tests/test_database.py
simba/tests/test_docling.py
simba/tests/test_document_ingestion_service.py
simba/tests/test_embedding.py
simba/tests/test_ingestion.py
simba/tests/test_update_db.py
simba/tests/test_vector_store_service.py
simba_core-1.0.1.dist-info/LICENCE
simba_core-1.0.1.dist-info/METADATA
simba_core-1.0.1.dist-info/WHEEL
simba_core-1.0.1.dist-info/entry_points.txt
simba_core-1.0.1.dist-info/RECORD
