Metadata-Version: 2.1
Name: simba-core
Version: 1.0.1
Summary: Knowledge Management System that connects to your RAG system
Home-page: https://github.com/GitHamza0206/simba
License: LICENCE.md
Keywords: rag,knowledge-management,vector-store,llm
Author: GitHamza0206
Author-email: zeroualihamza0206@gmail.com
Requires-Python: >=3.11,<3.13
Classifier: Development Status :: 4 - Beta
Classifier: Intended Audience :: Developers
Classifier: License :: OSI Approved :: Apache Software License
Classifier: License :: Other/Proprietary License
Classifier: Programming Language :: Python :: 3
Classifier: Programming Language :: Python :: 3.11
Classifier: Programming Language :: Python :: 3.12
Requires-Dist: celery (>=5.4.0,<6.0.0)
Requires-Dist: docling (>=2.15.1,<3.0.0)
Requires-Dist: faiss-cpu (>=1.9.0.post1,<2.0.0)
Requires-Dist: fastapi (>=0.115.6,<0.116.0)
Requires-Dist: ipykernel (>=6.29.5,<7.0.0)
Requires-Dist: langchain (>=0.3.13,<0.4.0)
Requires-Dist: langchain-chroma (>=0.1.4,<0.2.0)
Requires-Dist: langchain-community (>=0.3.13,<0.4.0)
Requires-Dist: langchain-docling (>=0.2.0,<0.3.0)
Requires-Dist: langchain-experimental (>=0.3.4,<0.4.0)
Requires-Dist: langchain-huggingface (>=0.1.2,<0.2.0)
Requires-Dist: langchain-milvus (>=0.1.8,<0.2.0)
Requires-Dist: langchain-ollama (>=0.2.2,<0.3.0)
Requires-Dist: langchain-openai (>=0.2.14,<0.3.0)
Requires-Dist: langgraph (>=0.2.60,<0.3.0)
Requires-Dist: litellm (>=1.56.6,<2.0.0)
Requires-Dist: markdown (>=3.7,<4.0)
Requires-Dist: markitdown (>=0.0.1a3,<0.0.2)
Requires-Dist: ollama (>=0.4.6,<0.5.0)
Requires-Dist: pdf2image (>=1.17.0,<2.0.0)
Requires-Dist: pdfminer-six (>=20240706,<20240707)
Requires-Dist: pillow-heif (>=0.21.0,<0.22.0)
Requires-Dist: pydantic-settings (>=2.7.1,<3.0.0)
Requires-Dist: pymupdf (>=1.25.2,<2.0.0)
Requires-Dist: pytest (>=8.3.4,<9.0.0)
Requires-Dist: pytest-asyncio (>=0.25.2,<0.26.0)
Requires-Dist: python-dotenv (>=1.0.1,<2.0.0)
Requires-Dist: python-multipart (>=0.0.20,<0.0.21)
Requires-Dist: rank-bm25 (>=0.2.2,<0.3.0)
Requires-Dist: rq (>=2.1.0,<3.0.0)
Requires-Dist: sentence-transformers (>=3.4.1,<4.0.0)
Requires-Dist: tinydb (>=4.8.2,<5.0.0)
Requires-Dist: torch (>=2.6.0,<3.0.0)
Requires-Dist: torchaudio (>=2.6.0,<3.0.0)
Requires-Dist: torchvision (>=0.21.0,<0.22.0)
Requires-Dist: unstructured[local-inference] (>=0.16.12,<0.17.0)
Requires-Dist: uvicorn (>=0.34.0,<0.35.0)
Project-URL: Repository, https://github.com/GitHamza0206/simba
